<?xml version="1.0" encoding="utf-8"?><Conciliation xmlns:xsd="http://schemas.stone.com/"><Header><GenerationDateTime>20230224203640</GenerationDateTime><StoneCode>880853854</StoneCode><LayoutVersion>2.2</LayoutVersion><FileId>0</FileId><ReferenceDate>20230109</ReferenceDate></Header><FinancialTransactions><Transaction><Events><CancellationCharges>0</CancellationCharges><Cancellations>0</Cancellations><Captures>1</Captures><ChargebackRefunds>0</ChargebackRefunds><Chargebacks>0</Chargebacks><Payments>0</Payments></Events><AcquirerTransactionKey>10932898722863</AcquirerTransactionKey><InitiatorTransactionKey>APOS-A8OVS-1673262293851</InitiatorTransactionKey><AuthorizationDateTime>20230109110459</AuthorizationDateTime><CaptureLocalDateTime>20230109080459</CaptureLocalDateTime><International>False</International><AccountType>2</AccountType><InstallmentType>1</InstallmentType><NumberOfInstallments>1</NumberOfInstallments><AuthorizedAmount>19.000000</AuthorizedAmount><CapturedAmount>19.000000</CapturedAmount><AuthorizationCurrencyCode>986</AuthorizationCurrencyCode><IssuerAuthorizationCode>645650</IssuerAuthorizationCode><BrandId>2</BrandId><CardNumber>555724******5641</CardNumber><Poi><PoiType>1</PoiType><SerialNumber>218sfa831856</SerialNumber></Poi><EntryMode>1</EntryMode><Installments><Installment><InstallmentNumber>1</InstallmentNumber><GrossAmount>19.000000</GrossAmount><NetAmount>18.487000</NetAmount><PrevisionPaymentDate>20230208</PrevisionPaymentDate></Installment></Installments></Transaction><Transaction><Events><CancellationCharges>0</CancellationCharges><Cancellations>0</Cancellations><Captures>1</Captures><ChargebackRefunds>0</ChargebackRefunds><Chargebacks>0</Chargebacks><Payments>0</Payments></Events><AcquirerTransactionKey>10932906590395</AcquirerTransactionKey><InitiatorTransactionKey>APOS-A8OVS-1673283213596</InitiatorTransactionKey><AuthorizationDateTime>20230109165335</AuthorizationDateTime><CaptureLocalDateTime>20230109135335</CaptureLocalDateTime><International>False</International><AccountType>2</AccountType><InstallmentType>1</InstallmentType><NumberOfInstallments>1</NumberOfInstallments><AuthorizedAmount>18.000000</AuthorizedAmount><CapturedAmount>18.000000</CapturedAmount><AuthorizationCurrencyCode>986</AuthorizationCurrencyCode><IssuerAuthorizationCode>838201</IssuerAuthorizationCode><BrandId>2</BrandId><CardNumber>544624******4009</CardNumber><Poi><PoiType>1</PoiType><SerialNumber>218sfa831856</SerialNumber></Poi><EntryMode>1</EntryMode><Installments><Installment><InstallmentNumber>1</InstallmentNumber><GrossAmount>18.000000</GrossAmount><NetAmount>17.514000</NetAmount><PrevisionPaymentDate>20230208</PrevisionPaymentDate></Installment></Installments></Transaction><Transaction><Events><CancellationCharges>0</CancellationCharges><Cancellations>0</Cancellations><Captures>1</Captures><ChargebackRefunds>0</ChargebackRefunds><Chargebacks>0</Chargebacks><Payments>0</Payments></Events><AcquirerTransactionKey>10932912469432</AcquirerTransactionKey><InitiatorTransactionKey>APOS-A8OVS-1673297013360</InitiatorTransactionKey><AuthorizationDateTime>20230109204345</AuthorizationDateTime><CaptureLocalDateTime>20230109174345</CaptureLocalDateTime><International>False</International><AccountType>2</AccountType><InstallmentType>1</InstallmentType><NumberOfInstallments>1</NumberOfInstallments><AuthorizedAmount>10.000000</AuthorizedAmount><CapturedAmount>10.000000</CapturedAmount><AuthorizationCurrencyCode>986</AuthorizationCurrencyCode><IssuerAuthorizationCode>064754</IssuerAuthorizationCode><BrandId>2</BrandId><CardNumber>534562******5832</CardNumber><Poi><PoiType>1</PoiType><SerialNumber>218sfa831856</SerialNumber></Poi><EntryMode>1</EntryMode><Installments><Installment><InstallmentNumber>1</InstallmentNumber><GrossAmount>10.000000</GrossAmount><NetAmount>9.730000</NetAmount><PrevisionPaymentDate>20230208</PrevisionPaymentDate></Installment></Installments></Transaction></FinancialTransactions><FinancialEvents /><FinancialTransactionsAccounts><Transaction><Events><CancellationCharges>0</CancellationCharges><Cancellations>0</Cancellations><Captures>0</Captures><ChargebackRefunds>0</ChargebackRefunds><Chargebacks>0</Chargebacks><Payments>1</Payments></Events><AcquirerTransactionKey>10631222588120</AcquirerTransactionKey><InitiatorTransactionKey>APOS-A8OVS-1673005856643</InitiatorTransactionKey><AuthorizationDateTime>20230106115059</AuthorizationDateTime><CaptureLocalDateTime>20230106085059</CaptureLocalDateTime><Poi><PoiType>1</PoiType><SerialNumber>218sfa831856</SerialNumber></Poi><EntryMode>1</EntryMode><Installments><Installment><InstallmentNumber>1</InstallmentNumber><GrossAmount>13.600000</GrossAmount><NetAmount>12.862282</NetAmount><PaymentDate>20230109</PaymentDate><AdvanceRateAmount>0.370518</AdvanceRateAmount><AdvancedReceivableOriginalPaymentDate>20230206</AdvancedReceivableOriginalPaymentDate><PaymentId>1611323807</PaymentId></Installment></Installments></Transaction><Transaction><Events><CancellationCharges>0</CancellationCharges><Cancellations>0</Cancellations><Captures>0</Captures><ChargebackRefunds>0</ChargebackRefunds><Chargebacks>0</Chargebacks><Payments>1</Payments></Events><AcquirerTransactionKey>10631222612825</AcquirerTransactionKey><InitiatorTransactionKey>APOS-A8OVS-1673006101790</InitiatorTransactionKey><AuthorizationDateTime>20230106115504</AuthorizationDateTime><CaptureLocalDateTime>20230106085504</CaptureLocalDateTime><Poi><PoiType>1</PoiType><SerialNumber>218sfa831856</SerialNumber></Poi><EntryMode>1</EntryMode><Installments><Installment><InstallmentNumber>1</InstallmentNumber><GrossAmount>7.500000</GrossAmount><NetAmount>7.093170</NetAmount><PaymentDate>20230109</PaymentDate><AdvanceRateAmount>0.204330</AdvanceRateAmount><AdvancedReceivableOriginalPaymentDate>20230206</AdvancedReceivableOriginalPaymentDate><PaymentId>1611323807</PaymentId></Installment></Installments></Transaction><Transaction><Events><CancellationCharges>0</CancellationCharges><Cancellations>0</Cancellations><Captures>0</Captures><ChargebackRefunds>0</ChargebackRefunds><Chargebacks>0</Chargebacks><Payments>1</Payments></Events><AcquirerTransactionKey>10631222624333</AcquirerTransactionKey><InitiatorTransactionKey>APOS-A8OVS-1673006211011</InitiatorTransactionKey><AuthorizationDateTime>20230106115657</AuthorizationDateTime><CaptureLocalDateTime>20230106085657</CaptureLocalDateTime><Poi><PoiType>1</PoiType><SerialNumber>218sfa831856</SerialNumber></Poi><EntryMode>1</EntryMode><Installments><Installment><InstallmentNumber>1</InstallmentNumber><GrossAmount>0.050000</GrossAmount><NetAmount>0.047288</NetAmount><PaymentDate>20230109</PaymentDate><AdvanceRateAmount>0.001362</AdvanceRateAmount><AdvancedReceivableOriginalPaymentDate>20230206</AdvancedReceivableOriginalPaymentDate><PaymentId>1611323807</PaymentId></Installment></Installments></Transaction><Transaction><Events><CancellationCharges>0</CancellationCharges><Cancellations>0</Cancellations><Captures>0</Captures><ChargebackRefunds>0</ChargebackRefunds><Chargebacks>0</Chargebacks><Payments>1</Payments></Events><AcquirerTransactionKey>10732854846788</AcquirerTransactionKey><InitiatorTransactionKey>APOS-A8OVS-1673098103628</InitiatorTransactionKey><AuthorizationDateTime>20230107132839</AuthorizationDateTime><CaptureLocalDateTime>20230107102839</CaptureLocalDateTime><Poi><PoiType>1</PoiType><SerialNumber>218sfa831856</SerialNumber></Poi><EntryMode>1</EntryMode><Installments><Installment><InstallmentNumber>1</InstallmentNumber><GrossAmount>17.000000</GrossAmount><NetAmount>16.039847</NetAmount><PaymentDate>20230109</PaymentDate><AdvanceRateAmount>0.462053</AdvanceRateAmount><AdvancedReceivableOriginalPaymentDate>20230206</AdvancedReceivableOriginalPaymentDate><PaymentId>1611323808</PaymentId></Installment></Installments></Transaction><Transaction><Events><CancellationCharges>0</CancellationCharges><Cancellations>0</Cancellations><Captures>0</Captures><ChargebackRefunds>0</ChargebackRefunds><Chargebacks>0</Chargebacks><Payments>1</Payments></Events><AcquirerTransactionKey>10732861271224</AcquirerTransactionKey><InitiatorTransactionKey>APOS-A8OVS-1673108943941</InitiatorTransactionKey><AuthorizationDateTime>20230107162907</AuthorizationDateTime><CaptureLocalDateTime>20230107132907</CaptureLocalDateTime><Poi><PoiType>1</PoiType><SerialNumber>218sfa831856</SerialNumber></Poi><EntryMode>1</EntryMode><Installments><Installment><InstallmentNumber>1</InstallmentNumber><GrossAmount>16.500000</GrossAmount><NetAmount>15.604974</NetAmount><PaymentDate>20230109</PaymentDate><AdvanceRateAmount>0.449526</AdvanceRateAmount><AdvancedReceivableOriginalPaymentDate>20230206</AdvancedReceivableOriginalPaymentDate><PaymentId>1611323807</PaymentId></Installment></Installments></Transaction><Transaction><Events><CancellationCharges>0</CancellationCharges><Cancellations>0</Cancellations><Captures>0</Captures><ChargebackRefunds>0</ChargebackRefunds><Chargebacks>0</Chargebacks><Payments>1</Payments></Events><AcquirerTransactionKey>10732870526477</AcquirerTransactionKey><InitiatorTransactionKey>APOS-A8OVS-1673129008342</InitiatorTransactionKey><AuthorizationDateTime>20230107220333</AuthorizationDateTime><CaptureLocalDateTime>20230107190333</CaptureLocalDateTime><Poi><PoiType>1</PoiType><SerialNumber>218sfa831856</SerialNumber></Poi><EntryMode>1</EntryMode><Installments><Installment><InstallmentNumber>1</InstallmentNumber><GrossAmount>21.500000</GrossAmount><NetAmount>20.333754</NetAmount><PaymentDate>20230109</PaymentDate><AdvanceRateAmount>0.585746</AdvanceRateAmount><AdvancedReceivableOriginalPaymentDate>20230206</AdvancedReceivableOriginalPaymentDate><PaymentId>1611323807</PaymentId></Installment></Installments></Transaction><Transaction><Events><CancellationCharges>0</CancellationCharges><Cancellations>0</Cancellations><Captures>0</Captures><ChargebackRefunds>0</ChargebackRefunds><Chargebacks>0</Chargebacks><Payments>1</Payments></Events><AcquirerTransactionKey>10832881280495</AcquirerTransactionKey><InitiatorTransactionKey>APOS-A8OVS-1673182335910</InitiatorTransactionKey><AuthorizationDateTime>20230108125235</AuthorizationDateTime><CaptureLocalDateTime>20230108095235</CaptureLocalDateTime><Poi><PoiType>1</PoiType><SerialNumber>218sfa831856</SerialNumber></Poi><EntryMode>1</EntryMode><Installments><Installment><InstallmentNumber>1</InstallmentNumber><GrossAmount>22.000000</GrossAmount><NetAmount>20.785226</NetAmount><PaymentDate>20230109</PaymentDate><AdvanceRateAmount>0.620774</AdvanceRateAmount><AdvancedReceivableOriginalPaymentDate>20230207</AdvancedReceivableOriginalPaymentDate><PaymentId>1611323807</PaymentId></Installment></Installments></Transaction><Transaction><Events><CancellationCharges>0</CancellationCharges><Cancellations>0</Cancellations><Captures>0</Captures><ChargebackRefunds>0</ChargebackRefunds><Chargebacks>0</Chargebacks><Payments>1</Payments></Events><AcquirerTransactionKey>10832881599332</AcquirerTransactionKey><InitiatorTransactionKey>APOS-A8OVS-1673183278244</InitiatorTransactionKey><AuthorizationDateTime>20230108130800</AuthorizationDateTime><CaptureLocalDateTime>20230108100800</CaptureLocalDateTime><Poi><PoiType>1</PoiType><SerialNumber>218sfa831856</SerialNumber></Poi><EntryMode>1</EntryMode><Installments><Installment><InstallmentNumber>1</InstallmentNumber><GrossAmount>13.000000</GrossAmount><NetAmount>12.803700</NetAmount><PaymentDate>20230109</PaymentDate><PaymentId>1610160274</PaymentId></Installment></Installments></Transaction><Transaction><Events><CancellationCharges>0</CancellationCharges><Cancellations>0</Cancellations><Captures>0</Captures><ChargebackRefunds>0</ChargebackRefunds><Chargebacks>0</Chargebacks><Payments>1</Payments></Events><AcquirerTransactionKey>10832887851991</AcquirerTransactionKey><InitiatorTransactionKey>APOS-A8OVS-1673198537631</InitiatorTransactionKey><AuthorizationDateTime>20230108172221</AuthorizationDateTime><CaptureLocalDateTime>20230108142221</CaptureLocalDateTime><Poi><PoiType>1</PoiType><SerialNumber>218sfa831856</SerialNumber></Poi><EntryMode>1</EntryMode><Installments><Installment><InstallmentNumber>1</InstallmentNumber><GrossAmount>47.500000</GrossAmount><NetAmount>44.877192</NetAmount><PaymentDate>20230109</PaymentDate><AdvanceRateAmount>1.340308</AdvanceRateAmount><AdvancedReceivableOriginalPaymentDate>20230207</AdvancedReceivableOriginalPaymentDate><PaymentId>1611323807</PaymentId></Installment></Installments></Transaction><Transaction><Events><CancellationCharges>0</CancellationCharges><Cancellations>0</Cancellations><Captures>0</Captures><ChargebackRefunds>0</ChargebackRefunds><Chargebacks>0</Chargebacks><Payments>1</Payments></Events><AcquirerTransactionKey>10832888449812</AcquirerTransactionKey><InitiatorTransactionKey>APOS-A8OVS-1673200592811</InitiatorTransactionKey><AuthorizationDateTime>20230108175641</AuthorizationDateTime><CaptureLocalDateTime>20230108145641</CaptureLocalDateTime><Poi><PoiType>1</PoiType><SerialNumber>218sfa831856</SerialNumber></Poi><EntryMode>1</EntryMode><Installments><Installment><InstallmentNumber>1</InstallmentNumber><GrossAmount>22.000000</GrossAmount><NetAmount>20.785226</NetAmount><PaymentDate>20230109</PaymentDate><AdvanceRateAmount>0.620774</AdvanceRateAmount><AdvancedReceivableOriginalPaymentDate>20230207</AdvancedReceivableOriginalPaymentDate><PaymentId>1611323807</PaymentId></Installment></Installments></Transaction><Transaction><Events><CancellationCharges>0</CancellationCharges><Cancellations>0</Cancellations><Captures>0</Captures><ChargebackRefunds>0</ChargebackRefunds><Chargebacks>0</Chargebacks><Payments>1</Payments></Events><AcquirerTransactionKey>10832892663112</AcquirerTransactionKey><InitiatorTransactionKey>APOS-A8OVS-1673216156485</InitiatorTransactionKey><AuthorizationDateTime>20230108221618</AuthorizationDateTime><CaptureLocalDateTime>20230108191618</CaptureLocalDateTime><Poi><PoiType>1</PoiType><SerialNumber>218sfa831856</SerialNumber></Poi><EntryMode>1</EntryMode><Installments><Installment><InstallmentNumber>1</InstallmentNumber><GrossAmount>15.000000</GrossAmount><NetAmount>14.171745</NetAmount><PaymentDate>20230109</PaymentDate><AdvanceRateAmount>0.423255</AdvanceRateAmount><AdvancedReceivableOriginalPaymentDate>20230207</AdvancedReceivableOriginalPaymentDate><PaymentId>1611323807</PaymentId></Installment></Installments></Transaction><Transaction><Events><CancellationCharges>0</CancellationCharges><Cancellations>0</Cancellations><Captures>0</Captures><ChargebackRefunds>0</ChargebackRefunds><Chargebacks>0</Chargebacks><Payments>1</Payments></Events><AcquirerTransactionKey>10832892742423</AcquirerTransactionKey><InitiatorTransactionKey>APOS-A8OVS-1673216435750</InitiatorTransactionKey><AuthorizationDateTime>20230108222038</AuthorizationDateTime><CaptureLocalDateTime>20230108192038</CaptureLocalDateTime><Poi><PoiType>1</PoiType><SerialNumber>218sfa831856</SerialNumber></Poi><EntryMode>1</EntryMode><Installments><Installment><InstallmentNumber>1</InstallmentNumber><GrossAmount>23.490000</GrossAmount><NetAmount>22.192953</NetAmount><PaymentDate>20230109</PaymentDate><AdvanceRateAmount>0.662817</AdvanceRateAmount><AdvancedReceivableOriginalPaymentDate>20230207</AdvancedReceivableOriginalPaymentDate><PaymentId>1611323807</PaymentId></Installment></Installments></Transaction></FinancialTransactionsAccounts><FinancialEventAccounts /><Payments><Payment><Id>1610160274</Id><WalletTypeId>5</WalletTypeId><TotalAmount>12.80</TotalAmount><TotalFinancialAccountsAmount>12.80</TotalFinancialAccountsAmount><LastNegativeAmount>0.00</LastNegativeAmount><FavoredBankAccount><BankCode>33</BankCode><BankBranch>1925</BankBranch><BankAccountNumber>130012936</BankAccountNumber></FavoredBankAccount></Payment><Payment><Id>1611323807</Id><WalletTypeId>7</WalletTypeId><TotalAmount>178.75</TotalAmount><TotalFinancialAccountsAmount>178.75</TotalFinancialAccountsAmount><LastNegativeAmount>0.00</LastNegativeAmount><FavoredBankAccount><BankCode>33</BankCode><BankBranch>1925</BankBranch><BankAccountNumber>130012936</BankAccountNumber></FavoredBankAccount></Payment><Payment><Id>1611323808</Id><WalletTypeId>13</WalletTypeId><TotalAmount>16.04</TotalAmount><TotalFinancialAccountsAmount>16.04</TotalFinancialAccountsAmount><LastNegativeAmount>0.00</LastNegativeAmount><FavoredBankAccount><BankCode>33</BankCode><BankBranch>1925</BankBranch><BankAccountNumber>130012936</BankAccountNumber></FavoredBankAccount></Payment></Payments><Trailer><CapturedTransactionsQuantity>3</CapturedTransactionsQuantity><CanceledTransactionsQuantity>0</CanceledTransactionsQuantity><PaidInstallmentsQuantity>12</PaidInstallmentsQuantity><ChargedCancellationsQuantity>0</ChargedCancellationsQuantity><ChargebacksQuantity>0</ChargebacksQuantity><ChargebacksRefundQuantity>0</ChargebacksRefundQuantity><ChargedChargebacksQuantity>0</ChargedChargebacksQuantity><PaidChargebacksRefundQuantity>0</PaidChargebacksRefundQuantity><PaidEventsQuantity>0</PaidEventsQuantity><ChargedEventsQuantity>0</ChargedEventsQuantity></Trailer></Conciliation>