<?xml version="1.0" encoding="utf-8"?><Conciliation xmlns:xsd="http://schemas.stone.com/"><Header><GenerationDateTime>20230224203639</GenerationDateTime><StoneCode>880853854</StoneCode><LayoutVersion>2.2</LayoutVersion><FileId>0</FileId><ReferenceDate>20230108</ReferenceDate></Header><FinancialTransactions><Transaction><Events><CancellationCharges>0</CancellationCharges><Cancellations>0</Cancellations><Captures>1</Captures><ChargebackRefunds>0</ChargebackRefunds><Chargebacks>0</Chargebacks><Payments>0</Payments></Events><AcquirerTransactionKey>10832881280495</AcquirerTransactionKey><InitiatorTransactionKey>APOS-A8OVS-1673182335910</InitiatorTransactionKey><AuthorizationDateTime>20230108125235</AuthorizationDateTime><CaptureLocalDateTime>20230108095235</CaptureLocalDateTime><International>False</International><AccountType>2</AccountType><InstallmentType>1</InstallmentType><NumberOfInstallments>1</NumberOfInstallments><AuthorizedAmount>22.000000</AuthorizedAmount><CapturedAmount>22.000000</CapturedAmount><AuthorizationCurrencyCode>986</AuthorizationCurrencyCode><IssuerAuthorizationCode>034129</IssuerAuthorizationCode><BrandId>2</BrandId><CardNumber>535858******8038</CardNumber><Poi><PoiType>1</PoiType><SerialNumber>218sfa831856</SerialNumber></Poi><EntryMode>1</EntryMode><Installments><Installment><InstallmentNumber>1</InstallmentNumber><GrossAmount>22.000000</GrossAmount><NetAmount>21.406000</NetAmount><PrevisionPaymentDate>20230207</PrevisionPaymentDate></Installment></Installments></Transaction><Transaction><Events><CancellationCharges>0</CancellationCharges><Cancellations>0</Cancellations><Captures>1</Captures><ChargebackRefunds>0</ChargebackRefunds><Chargebacks>0</Chargebacks><Payments>0</Payments></Events><AcquirerTransactionKey>10832881599332</AcquirerTransactionKey><InitiatorTransactionKey>APOS-A8OVS-1673183278244</InitiatorTransactionKey><AuthorizationDateTime>20230108130800</AuthorizationDateTime><CaptureLocalDateTime>20230108100800</CaptureLocalDateTime><International>False</International><AccountType>1</AccountType><InstallmentType>1</InstallmentType><NumberOfInstallments>1</NumberOfInstallments><AuthorizedAmount>13.000000</AuthorizedAmount><CapturedAmount>13.000000</CapturedAmount><AuthorizationCurrencyCode>986</AuthorizationCurrencyCode><IssuerAuthorizationCode>826046</IssuerAuthorizationCode><BrandId>2</BrandId><CardNumber>550209******6725</CardNumber><Poi><PoiType>1</PoiType><SerialNumber>218sfa831856</SerialNumber></Poi><EntryMode>1</EntryMode><Installments><Installment><InstallmentNumber>1</InstallmentNumber><GrossAmount>13.000000</GrossAmount><NetAmount>12.803700</NetAmount><PrevisionPaymentDate>20230109</PrevisionPaymentDate></Installment></Installments></Transaction><Transaction><Events><CancellationCharges>0</CancellationCharges><Cancellations>0</Cancellations><Captures>1</Captures><ChargebackRefunds>0</ChargebackRefunds><Chargebacks>0</Chargebacks><Payments>0</Payments></Events><AcquirerTransactionKey>10832887851991</AcquirerTransactionKey><InitiatorTransactionKey>APOS-A8OVS-1673198537631</InitiatorTransactionKey><AuthorizationDateTime>20230108172221</AuthorizationDateTime><CaptureLocalDateTime>20230108142221</CaptureLocalDateTime><International>False</International><AccountType>2</AccountType><InstallmentType>1</InstallmentType><NumberOfInstallments>1</NumberOfInstallments><AuthorizedAmount>47.500000</AuthorizedAmount><CapturedAmount>47.500000</CapturedAmount><AuthorizationCurrencyCode>986</AuthorizationCurrencyCode><IssuerAuthorizationCode>260906</IssuerAuthorizationCode><BrandId>2</BrandId><CardNumber>544624******4009</CardNumber><Poi><PoiType>1</PoiType><SerialNumber>218sfa831856</SerialNumber></Poi><EntryMode>1</EntryMode><Installments><Installment><InstallmentNumber>1</InstallmentNumber><GrossAmount>47.500000</GrossAmount><NetAmount>46.217500</NetAmount><PrevisionPaymentDate>20230207</PrevisionPaymentDate></Installment></Installments></Transaction><Transaction><Events><CancellationCharges>0</CancellationCharges><Cancellations>0</Cancellations><Captures>1</Captures><ChargebackRefunds>0</ChargebackRefunds><Chargebacks>0</Chargebacks><Payments>0</Payments></Events><AcquirerTransactionKey>10832888449812</AcquirerTransactionKey><InitiatorTransactionKey>APOS-A8OVS-1673200592811</InitiatorTransactionKey><AuthorizationDateTime>20230108175641</AuthorizationDateTime><CaptureLocalDateTime>20230108145641</CaptureLocalDateTime><International>False</International><AccountType>2</AccountType><InstallmentType>1</InstallmentType><NumberOfInstallments>1</NumberOfInstallments><AuthorizedAmount>22.000000</AuthorizedAmount><CapturedAmount>22.000000</CapturedAmount><AuthorizationCurrencyCode>986</AuthorizationCurrencyCode><IssuerAuthorizationCode>453611</IssuerAuthorizationCode><BrandId>2</BrandId><CardNumber>546997******9259</CardNumber><Poi><PoiType>1</PoiType><SerialNumber>218sfa831856</SerialNumber></Poi><EntryMode>1</EntryMode><Installments><Installment><InstallmentNumber>1</InstallmentNumber><GrossAmount>22.000000</GrossAmount><NetAmount>21.406000</NetAmount><PrevisionPaymentDate>20230207</PrevisionPaymentDate></Installment></Installments></Transaction><Transaction><Events><CancellationCharges>0</CancellationCharges><Cancellations>0</Cancellations><Captures>1</Captures><ChargebackRefunds>0</ChargebackRefunds><Chargebacks>0</Chargebacks><Payments>0</Payments></Events><AcquirerTransactionKey>10832892663112</AcquirerTransactionKey><InitiatorTransactionKey>APOS-A8OVS-1673216156485</InitiatorTransactionKey><AuthorizationDateTime>20230108221618</AuthorizationDateTime><CaptureLocalDateTime>20230108191618</CaptureLocalDateTime><International>False</International><AccountType>2</AccountType><InstallmentType>1</InstallmentType><NumberOfInstallments>1</NumberOfInstallments><AuthorizedAmount>15.000000</AuthorizedAmount><CapturedAmount>15.000000</CapturedAmount><AuthorizationCurrencyCode>986</AuthorizationCurrencyCode><IssuerAuthorizationCode>161866</IssuerAuthorizationCode><BrandId>2</BrandId><CardNumber>544731******0260</CardNumber><Poi><PoiType>1</PoiType><SerialNumber>218sfa831856</SerialNumber></Poi><EntryMode>1</EntryMode><Installments><Installment><InstallmentNumber>1</InstallmentNumber><GrossAmount>15.000000</GrossAmount><NetAmount>14.595000</NetAmount><PrevisionPaymentDate>20230207</PrevisionPaymentDate></Installment></Installments></Transaction><Transaction><Events><CancellationCharges>0</CancellationCharges><Cancellations>0</Cancellations><Captures>1</Captures><ChargebackRefunds>0</ChargebackRefunds><Chargebacks>0</Chargebacks><Payments>0</Payments></Events><AcquirerTransactionKey>10832892742423</AcquirerTransactionKey><InitiatorTransactionKey>APOS-A8OVS-1673216435750</InitiatorTransactionKey><AuthorizationDateTime>20230108222038</AuthorizationDateTime><CaptureLocalDateTime>20230108192038</CaptureLocalDateTime><International>False</International><AccountType>2</AccountType><InstallmentType>1</InstallmentType><NumberOfInstallments>1</NumberOfInstallments><AuthorizedAmount>23.490000</AuthorizedAmount><CapturedAmount>23.490000</CapturedAmount><AuthorizationCurrencyCode>986</AuthorizationCurrencyCode><IssuerAuthorizationCode>496725</IssuerAuthorizationCode><BrandId>2</BrandId><CardNumber>516292******4448</CardNumber><Poi><PoiType>1</PoiType><SerialNumber>218sfa831856</SerialNumber></Poi><EntryMode>1</EntryMode><Installments><Installment><InstallmentNumber>1</InstallmentNumber><GrossAmount>23.490000</GrossAmount><NetAmount>22.855770</NetAmount><PrevisionPaymentDate>20230207</PrevisionPaymentDate></Installment></Installments></Transaction></FinancialTransactions><FinancialEvents /><FinancialTransactionsAccounts /><FinancialEventAccounts /><Payments /><Trailer><CapturedTransactionsQuantity>6</CapturedTransactionsQuantity><CanceledTransactionsQuantity>0</CanceledTransactionsQuantity><PaidInstallmentsQuantity>0</PaidInstallmentsQuantity><ChargedCancellationsQuantity>0</ChargedCancellationsQuantity><ChargebacksQuantity>0</ChargebacksQuantity><ChargebacksRefundQuantity>0</ChargebacksRefundQuantity><ChargedChargebacksQuantity>0</ChargedChargebacksQuantity><PaidChargebacksRefundQuantity>0</PaidChargebacksRefundQuantity><PaidEventsQuantity>0</PaidEventsQuantity><ChargedEventsQuantity>0</ChargedEventsQuantity></Trailer></Conciliation>