<?xml version="1.0" encoding="utf-8"?><Conciliation xmlns:xsd="http://schemas.stone.com/"><Header><GenerationDateTime>20230225040029</GenerationDateTime><StoneCode>880853854</StoneCode><LayoutVersion>2.2</LayoutVersion><FileId>0</FileId><ReferenceDate>20220504</ReferenceDate></Header><FinancialTransactions /><FinancialEvents /><FinancialTransactionsAccounts><Transaction><Events><CancellationCharges>0</CancellationCharges><Cancellations>0</Cancellations><Captures>0</Captures><ChargebackRefunds>0</ChargebackRefunds><Chargebacks>0</Chargebacks><Payments>1</Payments></Events><AcquirerTransactionKey>22321429254743</AcquirerTransactionKey><InitiatorTransactionKey>APOS-A8OVS-1651579224736</InitiatorTransactionKey><AuthorizationDateTime>20220503120030</AuthorizationDateTime><CaptureLocalDateTime>20220503090030</CaptureLocalDateTime><Poi><PoiType>1</PoiType><SerialNumber>218sfa831856</SerialNumber></Poi><EntryMode>1</EntryMode><Installments><Installment><InstallmentNumber>1</InstallmentNumber><GrossAmount>9.000000</GrossAmount><NetAmount>8.864100</NetAmount><PaymentDate>20220504</PaymentDate><PaymentId>1250635458</PaymentId></Installment></Installments></Transaction><Transaction><Events><CancellationCharges>0</CancellationCharges><Cancellations>0</Cancellations><Captures>0</Captures><ChargebackRefunds>0</ChargebackRefunds><Chargebacks>0</Chargebacks><Payments>1</Payments></Events><AcquirerTransactionKey>22321430130460</AcquirerTransactionKey><InitiatorTransactionKey>APOS-A8OVS-1651582192155</InitiatorTransactionKey><AuthorizationDateTime>20220503124954</AuthorizationDateTime><CaptureLocalDateTime>20220503094954</CaptureLocalDateTime><Poi><PoiType>1</PoiType><SerialNumber>218sfa831856</SerialNumber></Poi><EntryMode>1</EntryMode><Installments><Installment><InstallmentNumber>1</InstallmentNumber><GrossAmount>10.000000</GrossAmount><NetAmount>9.447830</NetAmount><PaymentDate>20220504</PaymentDate><AdvanceRateAmount>0.282170</AdvanceRateAmount><AdvancedReceivableOriginalPaymentDate>20220602</AdvancedReceivableOriginalPaymentDate><PaymentId>1251586895</PaymentId></Installment></Installments></Transaction></FinancialTransactionsAccounts><FinancialEventAccounts /><Payments><Payment><Id>1251586895</Id><WalletTypeId>4</WalletTypeId><TotalAmount>9.45</TotalAmount><TotalFinancialAccountsAmount>9.45</TotalFinancialAccountsAmount><LastNegativeAmount>0.00</LastNegativeAmount><FavoredBankAccount><BankCode>33</BankCode><BankBranch>1925</BankBranch><BankAccountNumber>130012936</BankAccountNumber></FavoredBankAccount></Payment><Payment><Id>1250635458</Id><WalletTypeId>5</WalletTypeId><TotalAmount>8.86</TotalAmount><TotalFinancialAccountsAmount>8.86</TotalFinancialAccountsAmount><LastNegativeAmount>0.00</LastNegativeAmount><FavoredBankAccount><BankCode>33</BankCode><BankBranch>1925</BankBranch><BankAccountNumber>130012936</BankAccountNumber></FavoredBankAccount></Payment></Payments><Trailer><CapturedTransactionsQuantity>0</CapturedTransactionsQuantity><CanceledTransactionsQuantity>0</CanceledTransactionsQuantity><PaidInstallmentsQuantity>2</PaidInstallmentsQuantity><ChargedCancellationsQuantity>0</ChargedCancellationsQuantity><ChargebacksQuantity>0</ChargebacksQuantity><ChargebacksRefundQuantity>0</ChargebacksRefundQuantity><ChargedChargebacksQuantity>0</ChargedChargebacksQuantity><PaidChargebacksRefundQuantity>0</PaidChargebacksRefundQuantity><PaidEventsQuantity>0</PaidEventsQuantity><ChargedEventsQuantity>0</ChargedEventsQuantity></Trailer></Conciliation>