<?xml version="1.0" encoding="utf-8"?><Conciliation xmlns:xsd="http://schemas.stone.com/"><Header><GenerationDateTime>20230225015326</GenerationDateTime><StoneCode>880853854</StoneCode><LayoutVersion>2.2</LayoutVersion><FileId>0</FileId><ReferenceDate>20220320</ReferenceDate></Header><FinancialTransactions><Transaction><Events><CancellationCharges>0</CancellationCharges><Cancellations>0</Cancellations><Captures>1</Captures><ChargebackRefunds>0</ChargebackRefunds><Chargebacks>0</Chargebacks><Payments>0</Payments></Events><AcquirerTransactionKey>17921498916819</AcquirerTransactionKey><InitiatorTransactionKey>APOS-A8OVS-1647783597296</InitiatorTransactionKey><AuthorizationDateTime>20220320134009</AuthorizationDateTime><CaptureLocalDateTime>20220320104009</CaptureLocalDateTime><International>False</International><AccountType>2</AccountType><InstallmentType>1</InstallmentType><NumberOfInstallments>1</NumberOfInstallments><AuthorizedAmount>9.000000</AuthorizedAmount><CapturedAmount>9.000000</CapturedAmount><AuthorizationCurrencyCode>986</AuthorizationCurrencyCode><IssuerAuthorizationCode>400974</IssuerAuthorizationCode><BrandId>1</BrandId><CardNumber>410863******7366</CardNumber><Poi><PoiType>1</PoiType><SerialNumber>218sfa831856</SerialNumber></Poi><EntryMode>1</EntryMode><Installments><Installment><InstallmentNumber>1</InstallmentNumber><GrossAmount>9.000000</GrossAmount><NetAmount>8.757000</NetAmount><PrevisionPaymentDate>20220419</PrevisionPaymentDate></Installment></Installments></Transaction><Transaction><Events><CancellationCharges>0</CancellationCharges><Cancellations>0</Cancellations><Captures>1</Captures><ChargebackRefunds>0</ChargebackRefunds><Chargebacks>0</Chargebacks><Payments>0</Payments></Events><AcquirerTransactionKey>17921499382738</AcquirerTransactionKey><InitiatorTransactionKey>APOS-A8OVS-1647784816556</InitiatorTransactionKey><AuthorizationDateTime>20220320140019</AuthorizationDateTime><CaptureLocalDateTime>20220320110019</CaptureLocalDateTime><International>False</International><AccountType>1</AccountType><InstallmentType>1</InstallmentType><NumberOfInstallments>1</NumberOfInstallments><AuthorizedAmount>4.500000</AuthorizedAmount><CapturedAmount>4.500000</CapturedAmount><AuthorizationCurrencyCode>986</AuthorizationCurrencyCode><IssuerAuthorizationCode>033031</IssuerAuthorizationCode><BrandId>2</BrandId><CardNumber>550209******5587</CardNumber><Poi><PoiType>1</PoiType><SerialNumber>218sfa831856</SerialNumber></Poi><EntryMode>1</EntryMode><Installments><Installment><InstallmentNumber>1</InstallmentNumber><GrossAmount>4.500000</GrossAmount><NetAmount>4.432050</NetAmount><PrevisionPaymentDate>20220321</PrevisionPaymentDate></Installment></Installments></Transaction><Transaction><Events><CancellationCharges>0</CancellationCharges><Cancellations>0</Cancellations><Captures>1</Captures><ChargebackRefunds>0</ChargebackRefunds><Chargebacks>0</Chargebacks><Payments>0</Payments></Events><AcquirerTransactionKey>17921499397015</AcquirerTransactionKey><InitiatorTransactionKey>APOS-A8OVS-1647784842867</InitiatorTransactionKey><AuthorizationDateTime>20220320140055</AuthorizationDateTime><CaptureLocalDateTime>20220320110055</CaptureLocalDateTime><International>False</International><AccountType>1</AccountType><InstallmentType>1</InstallmentType><NumberOfInstallments>1</NumberOfInstallments><AuthorizedAmount>5.000000</AuthorizedAmount><CapturedAmount>5.000000</CapturedAmount><AuthorizationCurrencyCode>986</AuthorizationCurrencyCode><IssuerAuthorizationCode>308240</IssuerAuthorizationCode><BrandId>171</BrandId><CardNumber>506722******6856</CardNumber><Poi><PoiType>1</PoiType><SerialNumber>218sfa831856</SerialNumber></Poi><EntryMode>1</EntryMode><Installments><Installment><InstallmentNumber>1</InstallmentNumber><GrossAmount>5.000000</GrossAmount><NetAmount>4.912000</NetAmount><PrevisionPaymentDate>20220321</PrevisionPaymentDate></Installment></Installments></Transaction><Transaction><Events><CancellationCharges>0</CancellationCharges><Cancellations>0</Cancellations><Captures>1</Captures><ChargebackRefunds>0</ChargebackRefunds><Chargebacks>0</Chargebacks><Payments>0</Payments></Events><AcquirerTransactionKey>17921500701172</AcquirerTransactionKey><InitiatorTransactionKey>APOS-A8OVS-1647787832670</InitiatorTransactionKey><AuthorizationDateTime>20220320145045</AuthorizationDateTime><CaptureLocalDateTime>20220320115045</CaptureLocalDateTime><International>False</International><AccountType>2</AccountType><InstallmentType>1</InstallmentType><NumberOfInstallments>1</NumberOfInstallments><AuthorizedAmount>19.000000</AuthorizedAmount><CapturedAmount>19.000000</CapturedAmount><AuthorizationCurrencyCode>986</AuthorizationCurrencyCode><IssuerAuthorizationCode>146654</IssuerAuthorizationCode><BrandId>2</BrandId><CardNumber>550209******8059</CardNumber><Poi><PoiType>1</PoiType><SerialNumber>218sfa831856</SerialNumber></Poi><EntryMode>1</EntryMode><Installments><Installment><InstallmentNumber>1</InstallmentNumber><GrossAmount>19.000000</GrossAmount><NetAmount>18.487000</NetAmount><PrevisionPaymentDate>20220419</PrevisionPaymentDate></Installment></Installments></Transaction><Transaction><Events><CancellationCharges>0</CancellationCharges><Cancellations>0</Cancellations><Captures>1</Captures><ChargebackRefunds>0</ChargebackRefunds><Chargebacks>0</Chargebacks><Payments>0</Payments></Events><AcquirerTransactionKey>17921503263741</AcquirerTransactionKey><InitiatorTransactionKey>APOS-A8OVS-1647794480524</InitiatorTransactionKey><AuthorizationDateTime>20220320164139</AuthorizationDateTime><CaptureLocalDateTime>20220320134139</CaptureLocalDateTime><International>False</International><AccountType>1</AccountType><InstallmentType>1</InstallmentType><NumberOfInstallments>1</NumberOfInstallments><AuthorizedAmount>3.000000</AuthorizedAmount><CapturedAmount>3.000000</CapturedAmount><AuthorizationCurrencyCode>986</AuthorizationCurrencyCode><IssuerAuthorizationCode>238054</IssuerAuthorizationCode><BrandId>1</BrandId><CardNumber>471233******9856</CardNumber><Poi><PoiType>1</PoiType><SerialNumber>218sfa831856</SerialNumber></Poi><EntryMode>1</EntryMode><Installments><Installment><InstallmentNumber>1</InstallmentNumber><GrossAmount>3.000000</GrossAmount><NetAmount>2.954700</NetAmount><PrevisionPaymentDate>20220321</PrevisionPaymentDate></Installment></Installments></Transaction><Transaction><Events><CancellationCharges>0</CancellationCharges><Cancellations>0</Cancellations><Captures>1</Captures><ChargebackRefunds>0</ChargebackRefunds><Chargebacks>0</Chargebacks><Payments>0</Payments></Events><AcquirerTransactionKey>17921503281555</AcquirerTransactionKey><InitiatorTransactionKey>APOS-A8OVS-1647794540154</InitiatorTransactionKey><AuthorizationDateTime>20220320164238</AuthorizationDateTime><CaptureLocalDateTime>20220320134238</CaptureLocalDateTime><International>False</International><AccountType>2</AccountType><InstallmentType>1</InstallmentType><NumberOfInstallments>1</NumberOfInstallments><AuthorizedAmount>19.000000</AuthorizedAmount><CapturedAmount>19.000000</CapturedAmount><AuthorizationCurrencyCode>986</AuthorizationCurrencyCode><IssuerAuthorizationCode>024605</IssuerAuthorizationCode><BrandId>2</BrandId><CardNumber>535081******5716</CardNumber><Poi><PoiType>1</PoiType><SerialNumber>218sfa831856</SerialNumber></Poi><EntryMode>1</EntryMode><Installments><Installment><InstallmentNumber>1</InstallmentNumber><GrossAmount>19.000000</GrossAmount><NetAmount>18.487000</NetAmount><PrevisionPaymentDate>20220419</PrevisionPaymentDate></Installment></Installments></Transaction><Transaction><Events><CancellationCharges>0</CancellationCharges><Cancellations>0</Cancellations><Captures>1</Captures><ChargebackRefunds>0</ChargebackRefunds><Chargebacks>0</Chargebacks><Payments>0</Payments></Events><AcquirerTransactionKey>17921504299020</AcquirerTransactionKey><InitiatorTransactionKey>APOS-A8OVS-1647798343181</InitiatorTransactionKey><AuthorizationDateTime>20220320174557</AuthorizationDateTime><CaptureLocalDateTime>20220320144557</CaptureLocalDateTime><International>False</International><AccountType>1</AccountType><InstallmentType>1</InstallmentType><NumberOfInstallments>1</NumberOfInstallments><AuthorizedAmount>9.990000</AuthorizedAmount><CapturedAmount>9.990000</CapturedAmount><AuthorizationCurrencyCode>986</AuthorizationCurrencyCode><IssuerAuthorizationCode>884535</IssuerAuthorizationCode><BrandId>2</BrandId><CardNumber>550209******8844</CardNumber><Poi><PoiType>1</PoiType><SerialNumber>218sfa831856</SerialNumber></Poi><EntryMode>1</EntryMode><Installments><Installment><InstallmentNumber>1</InstallmentNumber><GrossAmount>9.990000</GrossAmount><NetAmount>9.839151</NetAmount><PrevisionPaymentDate>20220321</PrevisionPaymentDate></Installment></Installments></Transaction><Transaction><Events><CancellationCharges>0</CancellationCharges><Cancellations>0</Cancellations><Captures>1</Captures><ChargebackRefunds>0</ChargebackRefunds><Chargebacks>0</Chargebacks><Payments>0</Payments></Events><AcquirerTransactionKey>17921505625390</AcquirerTransactionKey><InitiatorTransactionKey>APOS-A8OVS-1647804076865</InitiatorTransactionKey><AuthorizationDateTime>20220320192121</AuthorizationDateTime><CaptureLocalDateTime>20220320162121</CaptureLocalDateTime><International>False</International><AccountType>2</AccountType><InstallmentType>1</InstallmentType><NumberOfInstallments>1</NumberOfInstallments><AuthorizedAmount>17.500000</AuthorizedAmount><CapturedAmount>17.500000</CapturedAmount><AuthorizationCurrencyCode>986</AuthorizationCurrencyCode><IssuerAuthorizationCode>328675</IssuerAuthorizationCode><BrandId>2</BrandId><CardNumber>550209******7639</CardNumber><Poi><PoiType>1</PoiType><SerialNumber>218sfa831856</SerialNumber></Poi><EntryMode>1</EntryMode><Installments><Installment><InstallmentNumber>1</InstallmentNumber><GrossAmount>17.500000</GrossAmount><NetAmount>17.027500</NetAmount><PrevisionPaymentDate>20220419</PrevisionPaymentDate></Installment></Installments></Transaction><Transaction><Events><CancellationCharges>0</CancellationCharges><Cancellations>0</Cancellations><Captures>1</Captures><ChargebackRefunds>0</ChargebackRefunds><Chargebacks>0</Chargebacks><Payments>0</Payments></Events><AcquirerTransactionKey>17921507441910</AcquirerTransactionKey><InitiatorTransactionKey>APOS-A8OVS-1647812062340</InitiatorTransactionKey><AuthorizationDateTime>20220320213438</AuthorizationDateTime><CaptureLocalDateTime>20220320183438</CaptureLocalDateTime><International>False</International><AccountType>1</AccountType><InstallmentType>1</InstallmentType><NumberOfInstallments>1</NumberOfInstallments><AuthorizedAmount>19.500000</AuthorizedAmount><CapturedAmount>19.500000</CapturedAmount><AuthorizationCurrencyCode>986</AuthorizationCurrencyCode><IssuerAuthorizationCode>571342</IssuerAuthorizationCode><BrandId>171</BrandId><CardNumber>506722******0137</CardNumber><Poi><PoiType>1</PoiType><SerialNumber>218sfa831856</SerialNumber></Poi><EntryMode>1</EntryMode><Installments><Installment><InstallmentNumber>1</InstallmentNumber><GrossAmount>19.500000</GrossAmount><NetAmount>19.156800</NetAmount><PrevisionPaymentDate>20220321</PrevisionPaymentDate></Installment></Installments></Transaction></FinancialTransactions><FinancialEvents /><FinancialTransactionsAccounts /><FinancialEventAccounts /><Payments /><Trailer><CapturedTransactionsQuantity>9</CapturedTransactionsQuantity><CanceledTransactionsQuantity>0</CanceledTransactionsQuantity><PaidInstallmentsQuantity>0</PaidInstallmentsQuantity><ChargedCancellationsQuantity>0</ChargedCancellationsQuantity><ChargebacksQuantity>0</ChargebacksQuantity><ChargebacksRefundQuantity>0</ChargebacksRefundQuantity><ChargedChargebacksQuantity>0</ChargedChargebacksQuantity><PaidChargebacksRefundQuantity>0</PaidChargebacksRefundQuantity><PaidEventsQuantity>0</PaidEventsQuantity><ChargedEventsQuantity>0</ChargedEventsQuantity></Trailer></Conciliation>